wryte.py
wryte-1.0.0.dist-info/LICENSE
wryte-1.0.0.dist-info/METADATA
wryte-1.0.0.dist-info/WHEEL
wryte-1.0.0.dist-info/entry_points.txt
wryte-1.0.0.dist-info/top_level.txt
wryte-1.0.0.dist-info/RECORD
