Metadata-Version: 2.1
Name: wryte
Version: 1.0.0
Summary: Simply Log
Home-page: https://github.com/strigo/wryte
Author: strigo.io
Author-email: ops@strigo.io
License: LICENSE
Platform: All
Classifier: Programming Language :: Python
Classifier: Programming Language :: Python :: 3.5
Classifier: Programming Language :: Python :: 3.6
Classifier: Programming Language :: Python :: 3.7
Classifier: Natural Language :: English
Classifier: Environment :: Console
Classifier: Intended Audience :: Developers
Classifier: Intended Audience :: Information Technology
Classifier: Intended Audience :: System Administrators
Classifier: License :: OSI Approved :: Apache Software License
Classifier: Operating System :: POSIX :: Linux
Classifier: Operating System :: Microsoft
Classifier: Topic :: Software Development :: Libraries :: Python Modules
Provides-Extra: cli
Requires-Dist: click (>=6.7) ; extra == 'cli'
Provides-Extra: color
Requires-Dist: colorama ; extra == 'color'
